optds_wrds/__init__.py
optds_wrds/py.typed
optds_wrds-0.1.0.dist-info/METADATA
optds_wrds-0.1.0.dist-info/WHEEL
optds_wrds-0.1.0.dist-info/RECORD
